kscale/__init__.py
kscale/cli.py
kscale/conf.py
kscale/py.typed
kscale/requirements-dev.txt
kscale/requirements.txt
kscale/artifacts/__init__.py
kscale/artifacts/plane.obj
kscale/artifacts/plane.urdf
kscale/utils/__init__.py
kscale/utils/api_base.py
kscale/utils/checksum.py
kscale/utils/cli.py
kscale/web/__init__.py
kscale/web/utils.py
kscale/web/cli/__init__.py
kscale/web/cli/clip.py
kscale/web/cli/group.py
kscale/web/cli/permission.py
kscale/web/cli/robot.py
kscale/web/cli/robot_class.py
kscale/web/cli/user.py
kscale/web/clients/__init__.py
kscale/web/clients/base.py
kscale/web/clients/client.py
kscale/web/clients/clip.py
kscale/web/clients/group.py
kscale/web/clients/permission.py
kscale/web/clients/robot.py
kscale/web/clients/robot_class.py
kscale/web/clients/user.py
kscale/web/gen/__init__.py
kscale/web/gen/api.py
kscale-0.3.18.dist-info/licenses/LICENSE
kscale-0.3.18.dist-info/METADATA
kscale-0.3.18.dist-info/WHEEL
kscale-0.3.18.dist-info/entry_points.txt
kscale-0.3.18.dist-info/top_level.txt
kscale-0.3.18.dist-info/RECORD
