Metadata-Version: 2.4
Name: kscale
Version: 0.3.18
Summary: The kscale project
Home-page: https://github.com/kscalelabs/kscale
Author: Benjamin Bolte
Requires-Python: >=3.11
License-File: LICENSE
Requires-Dist: omegaconf
Requires-Dist: email_validator
Requires-Dist: aiohttp
Requires-Dist: cryptography
Requires-Dist: httpx
Requires-Dist: pydantic
Requires-Dist: pyjwt
Requires-Dist: requests
Requires-Dist: yarl
Requires-Dist: aiofiles
Requires-Dist: click
Requires-Dist: colorlogging
Requires-Dist: tabulate
Requires-Dist: async-lru
Provides-Extra: dev
Requires-Dist: black; extra == "dev"
Requires-Dist: darglint; extra == "dev"
Requires-Dist: mypy; extra == "dev"
Requires-Dist: pytest; extra == "dev"
Requires-Dist: ruff; extra == "dev"
Requires-Dist: datamodel-code-generator; extra == "dev"
Dynamic: author
Dynamic: description
Dynamic: description-content-type
Dynamic: home-page
Dynamic: license-file
Dynamic: provides-extra
Dynamic: requires-dist
Dynamic: requires-python
Dynamic: summary
